{
	"animations": [
		{
			"offsets": [
				0,
				0
			],
			"indices": [],
			"fps": 24,
			"anim": "idle",
			"loop": false,
			"name": "tord_idle"
		},
		{
			"offsets": [
				5,
				-19
			],
			"indices": [],
			"fps": 24,
			"anim": "singDOWN",
			"loop": false,
			"name": "tord_down"
		},
		{
			"offsets": [
				-1,
				20
			],
			"indices": [],
			"fps": 24,
			"anim": "singUP",
			"loop": false,
			"name": "tord_up"
		},
		{
			"offsets": [
				63,
				-12
			],
			"indices": [],
			"fps": 24,
			"anim": "singLEFT",
			"loop": false,
			"name": "tord_right"
		},
		{
			"offsets": [
				-10,
				-18
			],
			"indices": [],
			"fps": 24,
			"anim": "singRIGHT",
			"loop": false,
			"name": "tord_left"
		}
	],
	"no_antialiasing": false,
	"image": "characters/tord_assets",
	"position": [
		30,
		90
	],
	"healthicon": "tordicons",
	"flip_x": false,
	"healthbar_colors": [
		204,
		51,
		51
	],
	"camera_position": [
		-10,
		-40
	],
	"sing_duration": 6.1,
	"scale": 1
}